[
  {
    "id": 4,
    "birth": "2023/02/27",
    "name": "타인의 사슬",
    "character": "뫼르소",
    "desc": {
      "desc1": [
        "수많은 것들이 옥죄어 온다···",
        "Meursault/타인의 사슬뫼르소.webp"
      ]
    },
    "egorank": "ZAYIN",
    "resistance": ["보통", "취약", "보통", "취약", "보통", "견딤", "보통"],
    "get": "기본",
    "abnormality": "고유 EGO",
    "ticket": "없음",
    "season": "0",
    "sync4": {
      "attack": 32,
      "mental": 10,
      "cost": [0, 0, 1, 0, 1, 0, 2],
      "skill1": {
        "skilltype": "공격",
        "name": "각성",
        "coin": 1,
        "type": "타격",
        "prop": "오만",
        "power": 19,
        "coinpower": 3,
        "weight": 1,
        "hit": {
          "start": "",
          "h1": "[적중시] 다음 턴에 속박 5 부여\n[적중시] 다음 턴에 속박 3 얻음\n[적중시] 다음 턴에 공격 위력 감소 4 부여\n[적중시] 다음 턴에 공격 위력 감소 3 얻음\n[앞면 적중시] 다음 턴에 보호 2 얻음",
          "h2": "",
          "h3": "",
          "h4": "",
          "h5": "",
          "end": ""
        }
      },
      "pass1": {
        "name": "판단 거부",
        "passdescription": "전투 시작 시 자신이 3개 이상의 스킬의 타겟이 되었다면, 보호 3을 얻음"
      }
    },
    "keyword": [
      "타인의 사슬",
      "뫼르소",
      "타격",
      "오만",
      "속박",
      "공격 위력 감소",
      "보호"
    ]
  }
]
