[
  {
    "id": 3,
    "birth": "2023/02/27",
    "name": "LCB 수감자",
    "character": "료슈",
    "sync": 4,
    "rank": 1,
    "description": "\"료슈. 요료슈쿠… 푸훗.\"",
    "resistance": ["내성", "보통", "취약"],
    "get": "기본",
    "position": "LCB",
    "ticket": "없음",
    "season": "0",
    "sync3": {
      "life": "146",
      "speed": "3-6",
      "defend": "31(-4)",
      "skill1": {
        "skilltype": "공격",
        "skill": "s1",
        "name": "칠하기",
        "coin": 1,
        "level": "37(+2)",
        "type": "참격",
        "prop": "탐식",
        "power": 3,
        "coinpower": 7,
        "weight": 1,
        "hit": {
          "start": "",
          "h1": "[적중시] 다음 턴에 호흡 2 얻음",
          "h2": "",
          "h3": "",
          "h4": "",
          "h5": "",
          "end": ""
        }
      },
      "skill2": {
        "skilltype": "공격",
        "skill": "s2",
        "name": "흩뿌리기",
        "coin": 2,
        "level": "37(+2)",
        "type": "참격",
        "prop": "색욕",
        "power": 4,
        "coinpower": 4,
        "weight": 1,
        "hit": {
          "start": "",
          "h1": "대상이 이번 턴에 피해를 받은 상태면 피해량 +30%",
          "h2": "대상이 이번 턴에 피해를 받은 상태면 피해량 +30%",
          "h3": "",
          "h4": "",
          "h5": "",
          "end": ""
        }
      },
      "skill3": {
        "skilltype": "공격",
        "skill": "s3",
        "name": "그려내기",
        "coin": 3,
        "level": "37(+2)",
        "type": "참격",
        "prop": "오만",
        "power": 5,
        "coinpower": 2,
        "weight": 1,
        "hit": {
          "start": "[전투 시작시] 참격 피해량 증가 2를 얻음",
          "h1": "",
          "h2": "",
          "h3": "",
          "h4": "",
          "h5": "",
          "end": ""
        }
      },
      "def": {
        "skilltype": "회피",
        "skill": "s4",
        "name": "회피",
        "coin": 1,
        "level": "33(-2)",
        "type": "회피",
        "catype": "",
        "prop": "없음",
        "power": 2,
        "coinpower": 10,
        "weight": 1,
        "hit": {
          "start": "",
          "h1": "",
          "h2": "",
          "h3": "",
          "h4": "",
          "h5": "",
          "end": ""
        }
      },
      "pass1": {
        "name": "무차별적 예술",
        "prop": "탐식",
        "poss": 3,
        "posstype": "공명",
        "passdescription": "자신이 받는 피해량 +25%, 가하는 피해량 +25%"
      },
      "pass2": {
        "name": "등떠밀기",
        "prop": "탐식",
        "poss": 3,
        "posstype": "공명",
        "passdescription": "최대 체력이 가장 낮은 아군 1명 가하는 피해량 +20%, 받는 피해량 +20%"
      }
    },
    "sync4": {
      "life": "146",
      "speed": "3-6",
      "defend": "31(-4)",
      "skill1": {
        "skilltype": "공격",
        "skill": "s1",
        "name": "칠하기",
        "coin": 1,
        "level": "37(+2)",
        "type": "참격",
        "prop": "탐식",
        "power": 4,
        "coinpower": 7,
        "weight": 1,
        "hit": {
          "start": "",
          "h1": "[적중시] 다음 턴에 호흡 2 얻음",
          "h2": "",
          "h3": "",
          "h4": "",
          "h5": "",
          "end": ""
        }
      },
      "skill2": {
        "skilltype": "공격",
        "skill": "s2",
        "name": "흩뿌리기",
        "coin": 2,
        "level": "37(+2)",
        "type": "참격",
        "prop": "색욕",
        "power": 4,
        "coinpower": 5,
        "weight": 1,
        "hit": {
          "start": "",
          "h1": "대상이 이번 턴에 피해를 받은 상태면 피해량 +30%",
          "h2": "대상이 이번 턴에 피해를 받은 상태면 피해량 +30%",
          "h3": "",
          "h4": "",
          "h5": "",
          "end": ""
        }
      },
      "skill3": {
        "skilltype": "공격",
        "skill": "s3",
        "name": "그려내기",
        "coin": 3,
        "level": "37(+2)",
        "type": "참격",
        "prop": "오만",
        "power": 5,
        "coinpower": 3,
        "weight": 1,
        "hit": {
          "start": "[전투 시작시] 참격 피해량 증가 2를 얻음",
          "h1": "",
          "h2": "[적중시] 다음 턴에 호흡 2 얻음",
          "h3": "",
          "h4": "",
          "h5": "",
          "end": ""
        }
      },
      "def": {
        "skilltype": "회피",
        "skill": "s4",
        "name": "회피",
        "coin": 1,
        "level": "33(-2)",
        "type": "회피",
        "catype": "",
        "prop": "탐식",
        "power": 2,
        "coinpower": 10,
        "weight": 1,
        "hit": {
          "start": "",
          "h1": "",
          "h2": "",
          "h3": "",
          "h4": "",
          "h5": "",
          "end": ""
        }
      },
      "pass1": {
        "name": "무차별적 예술",
        "prop": "탐식",
        "poss": 3,
        "posstype": "공명",
        "passdescription": "자신이 받는 피해량 +25%, 가하는 피해량 +25%"
      },
      "pass2": {
        "name": "등떠밀기",
        "prop": "탐식",
        "poss": 3,
        "posstype": "공명",
        "passdescription": "최대 체력이 가장 낮은 아군 1명 가하는 피해량 +20%, 받는 피해량 +20%"
      }
    },
    "keyword": [
      "LCB",
      "료슈",
      "참격",
      "탐식",
      "색욕",
      "오만",
      "호흡",
      "참격 피해량 증가"
    ],
    "desc": {
      "desc1": ["\"료슈. 요료슈쿠… 푸훗.\"", "RyoShu/LCB료슈일1.webp"]
    }
  },
  {
    "id": 15,
    "birth": "2023/02/27",
    "name": "남부 세븐 협회 6과",
    "character": "료슈",
    "sync": 4,
    "rank": 2,
    "resistance": ["내성", "보통", "취약"],
    "get": "추출(상시) / 파편 150 교환(상시)",
    "position": "세븐 협회",
    "ticket": "없음",
    "season": "0",
    "sync3": {
      "life": "139",
      "speed": "3-7",
      "defend": "31(-4)",
      "skill1": {
        "skilltype": "공격",
        "skill": "s1",
        "coin": 1,
        "name": "슬래시",
        "level": "40(+5)",
        "type": "타격",
        "prop": "나태",
        "power": 4,
        "coinpower": 6,
        "weight": 1,
        "hit": {
          "start": "",
          "h1": "[적중시] 파열 2 부여",
          "h2": "",
          "h3": "",
          "h4": "",
          "h5": "",
          "end": ""
        }
      },
      "skill2": {
        "skilltype": "공격",
        "skill": "s2",
        "coin": 1,
        "name": "어퍼 슬래시",
        "level": "40(+5)",
        "type": "참격",
        "prop": "오만",
        "power": 4,
        "coinpower": 12,
        "weight": 1,
        "hit": {
          "start": "대상에게 참격 취약이 있으면 스킬 위력 +2\n[합 승리시] 다음 턴에 공격 위력 증가 1 얻음",
          "h1": "[적중시] 방어 레벨 감소 2 부여",
          "h2": "",
          "h3": "",
          "h4": "",
          "h5": "",
          "end": ""
        }
      },
      "skill3": {
        "skilltype": "공격",
        "skill": "s3",
        "coin": 3,
        "name": "스워시",
        "level": "40(+5)",
        "type": "참격",
        "prop": "탐식",
        "power": 4,
        "coinpower": 5,
        "weight": 1,
        "hit": {
          "start": "[합 승리시] 이 스킬에서 부여하는 참격 취약 2 추가 부여",
          "h1": "[적중시] 다음 턴에 참격 취약 3 부여",
          "h2": "",
          "h3": "",
          "h4": "",
          "h5": "",
          "end": ""
        }
      },
      "def": {
        "skilltype": "수비",
        "skill": "s4",
        "coin": 1,
        "name": "반격",
        "level": "35(0)",
        "catype": "참격",
        "type": "반격",
        "prop": "탐식",
        "power": 8,
        "coinpower": 4,
        "weight": 1,
        "hit": {
          "start": "",
          "h1": "",
          "h2": "",
          "h3": "",
          "h4": "",
          "h5": "",
          "end": ""
        }
      },
      "pass1": {
        "name": "반.갈",
        "prop": "탐식",
        "poss": 5,
        "posstype": "보유",
        "passdescription": "이번 턴 참격 피해량 +10%"
      },
      "pass2": {
        "name": "아이스 브레이킹",
        "prop": "탐식",
        "poss": 4,
        "posstype": "보유",
        "passdescription": "최대 체력이 가장 낮은 아군 1명 파열 부여 값 +1"
      }
    },
    "sync4": {
      "life": "139",
      "speed": "3-7",
      "defend": "31(-4)",
      "skill1": {
        "skilltype": "공격",
        "skill": "s1",
        "coin": 1,
        "name": "슬래시",
        "level": "40(+5)",
        "type": "타격",
        "prop": "나태",
        "power": 4,
        "coinpower": 8,
        "weight": 1,
        "hit": {
          "start": "",
          "h1": "[적중시] 파열 2 부여",
          "h2": "",
          "h3": "",
          "h4": "",
          "h5": "",
          "end": ""
        }
      },
      "skill2": {
        "skilltype": "공격",
        "skill": "s2",
        "coin": 1,
        "name": "어퍼 슬래시",
        "level": "40(+5)",
        "type": "참격",
        "prop": "오만",
        "power": 4,
        "coinpower": 14,
        "weight": 1,
        "hit": {
          "start": "대상에게 참격 취약이 있으면 스킬 위력 +2\n[합 승리시] 다음 턴에 공격 위력 증가 1 얻음",
          "h1": "[적중시] 방어 레벨 감소 2 부여",
          "h2": "",
          "h3": "",
          "h4": "",
          "h5": "",
          "end": ""
        }
      },
      "skill3": {
        "skilltype": "공격",
        "skill": "s3",
        "coin": 3,
        "name": "스워시",
        "level": "40(+5)",
        "type": "참격",
        "prop": "탐식",
        "power": 4,
        "coinpower": 5,
        "weight": 1,
        "hit": {
          "start": "[합 승리시] 이 스킬에서 부여하는 참격 취약 2 추가 부여",
          "h1": "[적중시] 다음 턴에 참격 취약 3 부여",
          "h2": "",
          "h3": "",
          "h4": "",
          "h5": "",
          "end": ""
        }
      },
      "def": {
        "skilltype": "수비",
        "skill": "s4",
        "coin": 1,
        "name": "반격",
        "level": "35(0)",
        "catype": "참격",
        "type": "반격",
        "prop": "탐식",
        "power": 8,
        "coinpower": 4,
        "weight": 1,
        "hit": {
          "start": "",
          "h1": "[적중시] 참격 취약 1 부여",
          "h2": "",
          "h3": "",
          "h4": "",
          "h5": "",
          "end": ""
        }
      },
      "pass1": {
        "name": "반.갈",
        "prop": "탐식",
        "poss": 5,
        "posstype": "보유",
        "passdescription": "이번 턴 참격 피해량 +10%"
      },
      "pass2": {
        "name": "아이스 브레이킹",
        "prop": "탐식",
        "poss": 4,
        "posstype": "보유",
        "passdescription": "최대 체력이 가장 낮은 아군 1명 파열 부여 값 +1"
      }
    },
    "keyword": [
      "세븐 협회",
      "료슈",
      "타격",
      "참격",
      "나태",
      "오만",
      "탐식",
      "파열",
      "공격 위력 증가",
      "방어 레벨 감소",
      "참격 취약"
    ],
    "desc": {
      "desc1": [
        "\"넌… 예술의 극치를 본 적 있나? 난 그걸 찾기 위해 왔어.\"",
        "RyoShu/세븐 협회료슈일1.webp"
      ],
      "desc2": ["\"흥, 이미 예상하고 있었지.\"", "RyoShu/세븐 협회료슈일2.webp"]
    }
  },
  {
    "id": 30,
    "birth": "2023/02/27",
    "name": "흑운회 와카슈",
    "character": "료슈",
    "sync": 4,
    "rank": 3,
    "resistance": ["취약", "내성", "보통"],
    "get": "추출 / 파편 400 교환(상시)",
    "position": "흑운회",
    "ticket": "없음",
    "season": "0",
    "sync3": {
      "life": "161",
      "speed": "3-6",
      "defend": 35,
      "skill1": {
        "skilltype": "공격",
        "skill": "s1",
        "coin": 1,
        "name": "발경",
        "level": 38,
        "type": "관통",
        "prop": "탐식",
        "power": 5,
        "coinpower": 6,
        "weight": 1,
        "hit": {
          "start": "",
          "h1": "[적중시] 마비 3 부여",
          "h2": "",
          "h3": "",
          "h4": "",
          "h5": "",
          "end": ""
        }
      },
      "skill2": {
        "skilltype": "공격",
        "skill": "s2",
        "coin": 2,
        "name": "뒷처리",
        "level": 38,
        "type": "관통",
        "prop": "오만",
        "power": 5,
        "coinpower": 5,
        "weight": 1,
        "hit": {
          "start": "",
          "h1": "[적중시] 출혈 2 부여",
          "h2": "[앞면 적중시] 출혈 횟수 1 증가\n[앞면 적중시] 피해량 감소 2 부여",
          "h3": "",
          "h4": "",
          "h5": "",
          "end": ""
        }
      },
      "skill3": {
        "skilltype": "공격",
        "skill": "s3",
        "coin": 2,
        "name": "구름 휘젓기",
        "level": 38,
        "type": "관통",
        "prop": "색욕",
        "power": 8,
        "coinpower": 4,
        "weight": 1,
        "hit": {
          "start": "",
          "h1": "[앞면 적중시] 출혈 2 부여",
          "h2": "[적중시] 출혈 횟수 3 증가\n[적중시] 공격 레벨 감소 5 부여",
          "h3": "",
          "h4": "",
          "h5": "",
          "end": ""
        }
      },
      "def": {
        "skilltype": "수비",
        "skill": "s4",
        "coin": 1,
        "name": "가드",
        "level": 35,
        "catype": "",
        "type": "방어",
        "prop": "없음",
        "power": 10,
        "coinpower": 4,
        "weight": 1,
        "hit": {
          "start": "",
          "h1": "",
          "h2": "",
          "h3": "",
          "h4": "",
          "h5": "",
          "end": ""
        }
      },
      "pass1": {
        "name": "흑운도",
        "prop": "색욕",
        "poss": 3,
        "posstype": "공명",
        "passdescription": "출혈이 부여된 적 공격 시 피해량 +10%"
      },
      "pass2": {
        "name": "행동대장",
        "prop": "색욕",
        "poss": 4,
        "posstype": "보유",
        "passdescription": "속도가 가장 높은 아군 1명 출혈 부여 값 +1"
      }
    },
    "sync4": {
      "life": "161",
      "speed": "3-6",
      "defend": 35,
      "skill1": {
        "skilltype": "공격",
        "skill": "s1",
        "coin": 1,
        "name": "발경",
        "level": 38,
        "type": "관통",
        "prop": "탐식",
        "power": 5,
        "coinpower": 6,
        "weight": 1,
        "hit": {
          "start": "대상의 출혈 횟수가 2 이상이면, 피해량 +20%",
          "h1": "[적중시] 마비 3 부여",
          "h2": "",
          "h3": "",
          "h4": "",
          "h5": "",
          "end": ""
        }
      },
      "skill2": {
        "skilltype": "공격",
        "skill": "s2",
        "coin": 2,
        "name": "뒷처리",
        "level": 38,
        "type": "관통",
        "prop": "오만",
        "power": 5,
        "coinpower": 5,
        "weight": 1,
        "hit": {
          "start": "대상의 출혈 횟수가 5 이상이면, 피해량 +20%",
          "h1": "[적중시] 출혈 2 부여",
          "h2": "[적중시] 출혈 횟수 3 증가\n[앞면 적중시] 피해량 감소 2 부여",
          "h3": "",
          "h4": "",
          "h5": "",
          "end": ""
        }
      },
      "skill3": {
        "skilltype": "공격",
        "skill": "s3",
        "coin": 2,
        "name": "구름 휘젓기",
        "level": 38,
        "type": "관통",
        "prop": "색욕",
        "power": 8,
        "coinpower": 4,
        "weight": 1,
        "hit": {
          "start": "대상의 출혈 횟수가 9 이상이면, 피해량 +40%",
          "h1": "[앞면 적중시] 출혈 2 부여",
          "h2": "[적중시] 출혈 횟수 3 증가\n[적중시] 공격 레벨 감소 5 부여",
          "h3": "",
          "h4": "",
          "h5": "",
          "end": ""
        }
      },
      "def": {
        "skilltype": "수비",
        "skill": "s4",
        "coin": 1,
        "name": "가드",
        "level": 35,
        "catype": "",
        "type": "방어",
        "prop": "색욕",
        "power": 10,
        "coinpower": 6,
        "weight": 1,
        "hit": {
          "start": "",
          "h1": "",
          "h2": "",
          "h3": "",
          "h4": "",
          "h5": "",
          "end": ""
        }
      },
      "pass1": {
        "name": "흑운도",
        "prop": "색욕",
        "poss": 3,
        "posstype": "공명",
        "passdescription": "출혈이 부여된 적 공격 시 피해량 +10%"
      },
      "pass2": {
        "name": "행동대장",
        "prop": "색욕",
        "poss": 4,
        "posstype": "보유",
        "passdescription": "속도가 가장 높은 아군 1명 출혈 부여 값 +1"
      }
    },
    "keyword": [
      "흑운회",
      "료슈",
      "관통",
      "탐식",
      "오만",
      "색욕",
      "출혈",
      "마비",
      "출혈 횟수",
      "피해량 감소",
      "공격 레벨 감소"
    ],
    "desc": {
      "desc1": [
        "\"거슬리는 게 있다면… 난 그림자조차 베어버려.\"",
        "RyoShu/흑운회료슈일1.webp"
      ],
      "desc2": ["\"궁극의 검술을 보여주지!\"", "RyoShu/흑운회료슈일2.webp"]
    }
  },
  {
    "id": 45,
    "birth": "2023/03/23",
    "name": "료.고.파. 주방장",
    "character": "료슈",
    "sync": 4,
    "rank": 3,
    "resistance": ["내성", "취약", "보통"],
    "get": "헬스 치킨 이벤트 / 파편 400 교환(시즌 1 / 시즌 3 이후)",
    "ticket": "없음",
    "season": "1 이벤트",
    "position": "23구 뒷골목",
    "desc": {
      "desc1": [
        "\"왔나? 파이 하나 먹고 갈래?\"",
        "RyoShu/23구 뒷골목료슈일1.webp"
      ],
      "desc2": [
        "\"드디어, 여덟 명 중 한 명이... 아니야? 쯧, 그럼 관심 없어.\"",
        "RyoShu/23구 뒷골목료슈일2.webp"
      ]
    },
    "sync3": {
      "life": 154,
      "speed": "3-6",
      "defend": 33,
      "skill1": {
        "skilltype": "공격",
        "skill": "s1",
        "coin": 2,
        "name": "요.준",
        "level": 38,
        "type": "참격",
        "prop": "분노",
        "power": 4,
        "coinpower": 3,
        "weight": 1,
        "hit": {
          "start": "",
          "h1": "[적중시] 출혈 횟수 1 증가",
          "h2": "[적중시] 갈증 1 얻음",
          "h3": "",
          "h4": "",
          "h5": "",
          "end": ""
        }
      },
      "skill2": {
        "skilltype": "공격",
        "skill": "s2",
        "coin": 3,
        "name": "재.사",
        "level": 38,
        "type": "관통",
        "prop": "질투",
        "power": 3,
        "coinpower": 5,
        "weight": 1,
        "hit": {
          "start": "",
          "h1": "[적중시] 다음 턴에 속박 1 부여",
          "h2": "[앞면 적중시] 출혈 2 부여",
          "h3": "[적중시] 대상에게 출혈 또는 마비가 있다면 다음 턴에 체력 회복 감소 3 부여",
          "h4": "",
          "h5": "",
          "end": ""
        }
      },
      "skill3": {
        "skilltype": "공격",
        "skill": "s3",
        "coin": 4,
        "name": "무엇이든 요리할 수 있지",
        "level": 38,
        "type": "참격",
        "prop": "색욕",
        "power": 3,
        "coinpower": 3,
        "weight": 1,
        "hit": {
          "start": "대상이 잃은 체력의 5%만큼 피해량이 증가함 (최대 20)",
          "h1": "[앞면 적중시] 마지막 코인의 피해량 10% 증가",
          "h2": "[앞면 적중시] 마지막 코인의 피해량 5% 증가",
          "h3": "[앞면 적중시] 마지막 코인의 피해량 5% 증가",
          "h4": "",
          "h5": "",
          "end": ""
        }
      },
      "def": {
        "skilltype": "수비",
        "skill": "s4",
        "coin": 1,
        "name": "신.재 발견",
        "level": 37,
        "catype": "",
        "type": "회피",
        "prop": "없음",
        "power": 4,
        "coinpower": 10,
        "weight": 1,
        "hit": {
          "start": "[회피 성공시] 다음 턴에 신속 1 얻음",
          "h1": "",
          "h2": "",
          "h3": "",
          "h4": "",
          "h5": "",
          "end": ""
        }
      },
      "pass1": {
        "name": "즉흥 조리",
        "prop": "색욕",
        "poss": 5,
        "posstype": "보유",
        "passdescription": "적 처치 시 체력이 가장 낮은 아군 1명의 체력 15 회복(턴당 1회 발동). 갈증이 있는 경우 전부 소모하고, 소모한 갈증에 비례하여 체력 회복량 증가"
      },
      "pass2": {
        "name": "예술적인 맛",
        "prop": "색욕",
        "poss": 5,
        "posstype": "보유",
        "passdescription": "체적 사망 시 체력이 가장 낮은 아군 1명의 체력 15 회복"
      }
    },
    "sync4": {
      "life": 154,
      "speed": "3-6",
      "defend": 33,
      "skill1": {
        "skilltype": "공격",
        "skill": "s1",
        "coin": 2,
        "name": "요.준",
        "level": 38,
        "type": "참격",
        "prop": "분노",
        "power": 4,
        "coinpower": 3,
        "weight": 1,
        "hit": {
          "start": "",
          "h1": "[적중시] 출혈 횟수 1 증가",
          "h2": "[적중시] 갈증 2 얻음",
          "h3": "",
          "h4": "",
          "h5": "",
          "end": ""
        }
      },
      "skill2": {
        "skilltype": "공격",
        "skill": "s2",
        "coin": 3,
        "name": "재.사",
        "level": 38,
        "type": "관통",
        "prop": "질투",
        "power": 3,
        "coinpower": 5,
        "weight": 1,
        "hit": {
          "start": "[사용시] 갈증 1 얻음",
          "h1": "[적중시] 다음 턴에 속박 1 부여",
          "h2": "[앞면 적중시] 출혈 3 부여",
          "h3": "[적중시] 대상에게 출혈 또는 마비가 있다면 다음 턴에 체력 회복 감소 4 부여",
          "h4": "",
          "h5": "",
          "end": ""
        }
      },
      "skill3": {
        "skilltype": "공격",
        "skill": "s3",
        "coin": 4,
        "name": "무엇이든 요리할 수 있지",
        "level": 38,
        "type": "참격",
        "prop": "색욕",
        "power": 3,
        "coinpower": 3,
        "weight": 1,
        "hit": {
          "start": "대상이 잃은 체력의 5%만큼 피해량이 증가함 (최대 20)",
          "h1": "[앞면 적중시] 마지막 코인의 피해량 10% 증가",
          "h2": "[앞면 적중시] 마지막 코인의 피해량 5% 증가",
          "h3": "[앞면 적중시] 마지막 코인의 피해량 5% 증가",
          "h4": "",
          "h5": "",
          "end": ""
        }
      },
      "def": {
        "skilltype": "수비",
        "skill": "s4",
        "coin": 1,
        "name": "신.재 발견",
        "level": 37,
        "catype": "",
        "type": "회피",
        "prop": "색욕",
        "power": 4,
        "coinpower": 10,
        "weight": 1,
        "hit": {
          "start": "[회피 성공시] 다음 턴에 신속 1 얻음",
          "h1": "",
          "h2": "",
          "h3": "",
          "h4": "",
          "h5": "",
          "end": ""
        }
      },
      "pass1": {
        "name": "즉흥 조리",
        "prop": "색욕",
        "poss": 5,
        "posstype": "보유",
        "passdescription": "적 처치 시 체력이 가장 낮은 아군 1명의 체력 15 회복(턴당 1회 발동). 갈증이 있는 경우 전부 소모하고, 소모한 갈증에 비례하여 체력 회복량 증가"
      },
      "pass2": {
        "name": "예술적인 맛",
        "prop": "색욕",
        "poss": 5,
        "posstype": "보유",
        "passdescription": "체적 사망 시 체력이 가장 낮은 아군 1명의 체력 15 회복"
      }
    },
    "keyword": [
      "료고파",
      "료슈",
      "참격",
      "관통",
      "분노",
      "질투",
      "색욕",
      "출혈 횟수",
      "갈증",
      "속박",
      "출혈",
      "마비",
      "체력 회복 감소",
      "신속",
      "체력 회복"
    ]
  },
  {
    "id": 66,
    "birth": "2023/08/24",
    "name": "W사 3등급 정리요원",
    "character": "료슈",
    "sync": 4,
    "rank": 3,
    "resistance": ["내성", "보통", "취약"],
    "get": "추출 / 파편 400 교환(상시)",
    "ticket": "\"어이가 없군. [교육]이나 하고 있으라니.\"",
    "season": "0",
    "position": "W사",
    "desc": {
      "desc1": [
        "\"어이가 없군. 병.솔.이나 하고 있으라니.\"",
        "RyoShu/W사료슈일1.webp"
      ],
      "desc2": [
        "\"흥, 실력을 인정했다면 사람 관리 말고 현장 청소 업무에 나를 배치해라.\"",
        "RyoShu/W사료슈일2.webp"
      ]
    },
    "sync3": {
      "life": 146,
      "speed": "3-6",
      "defend": 31,
      "skill1": {
        "skilltype": "공격",
        "skill": "s1",
        "coin": 3,
        "name": "에.순",
        "level": 40,
        "type": "참격",
        "prop": "색욕",
        "power": 3,
        "coinpower": 3,
        "weight": 1,
        "hit": {
          "start": "충전 횟수가 10 이상이면, 피해량 +10%",
          "h1": "[적중시] 자신의 충전 횟수 2 증가",
          "h2": "[적중시] 자신의 충전 횟수 2 증가",
          "h3": "",
          "h4": "",
          "h5": "",
          "end": ""
        }
      },
      "skill2": {
        "skilltype": "공격",
        "skill": "s2",
        "coin": 3,
        "name": "도약",
        "level": 40,
        "type": "참격",
        "prop": "오만",
        "power": 2,
        "coinpower": 5,
        "weight": 1,
        "hit": {
          "start": "[사용시] 자신의 충전 횟수 6 증가\n충전 횟수가 10 이상이면, 코인 위력 +1",
          "h1": "[적중시] 충전 횟수가 10 이상이면, 참격 취약 1 부여",
          "h2": "",
          "h3": "[적중시] 대상의 체력이 30% 미만이면 피해량 +20%\n[적 처치시] 다음 턴에 신속 2 얻음",
          "h4": "",
          "h5": "",
          "end": ""
        }
      },
      "skill3": {
        "skilltype": "공격",
        "skill": "s3",
        "coin": 4,
        "name": "차.마.공.절",
        "level": 40,
        "type": "참격",
        "prop": "질투",
        "power": 3,
        "coinpower": 2,
        "weight": 1,
        "hit": {
          "start": "[사용시] 충전 횟수가 7 이상, 15 미만이면, 보유한 충전 횟수를 전부 소모한 뒤, 최대 체력의 3x(15-소모한 충전 횟수)%만큼 체력을 소모하여 코인 위력 +5\n[사용시] 충전 횟수를 15 소모하여 코인 위력 +5",
          "h1": "[앞면 적중시] 마지막 코인의 피해량 +5%",
          "h2": "[앞면 적중시] 마지막 코인의 피해량 +5%",
          "h3": "[앞면 적중시] 마지막 코인의 피해량 +5%",
          "h4": "[적 처치시] 스킬 사용시 충전 횟수를 15 소모했다면, 자신과 자신을 제외한 무작위 아군 1명에게 충전 역장 5 부여",
          "h5": "",
          "end": ""
        }
      },
      "def": {
        "skilltype": "수비",
        "skill": "s4",
        "coin": 1,
        "name": "충전 회피",
        "level": 31,
        "catype": "",
        "type": "방어",
        "prop": "없음",
        "power": 3,
        "coinpower": 10,
        "weight": 1,
        "hit": {
          "start": "충전 횟수 5당 기본 위력 +1(최대 2)",
          "h1": "",
          "h2": "",
          "h3": "",
          "h4": "",
          "h5": "",
          "end": ""
        }
      },
      "pass1": {
        "name": "차원 마검",
        "prop": "오만",
        "poss": 5,
        "posstype": "보유",
        "passdescription": "적 처치 시 충전 횟수 2 증가(턴 당 최대 3회 발동)"
      },
      "pass2": {
        "name": "차원 굴절 칼날 - Type: Blade Mk7",
        "prop": "오만",
        "poss": 5,
        "posstype": "보유",
        "passdescription": "최대 체력이 가장 낮은 아군 1명이 적 처치 시 충전 횟수 2 증가(턴 당 최대 1회 발동)"
      }
    },
    "sync4": {
      "life": 146,
      "speed": "3-6",
      "defend": 31,
      "skill1": {
        "skilltype": "공격",
        "skill": "s1",
        "coin": 3,
        "name": "에.순",
        "level": 40,
        "type": "참격",
        "prop": "색욕",
        "power": 3,
        "coinpower": 3,
        "weight": 1,
        "hit": {
          "start": "충전 횟수가 10 이상이면, 피해량 +10%\n충전 횟수가 15 이상이면, 추가로 피해량 +10%",
          "h1": "[적중시] 자신의 충전 횟수 2 증가",
          "h2": "[적중시] 자신의 충전 횟수 2 증가",
          "h3": "",
          "h4": "",
          "h5": "",
          "end": ""
        }
      },
      "skill2": {
        "skilltype": "공격",
        "skill": "s2",
        "coin": 3,
        "name": "도약",
        "level": 40,
        "type": "참격",
        "prop": "오만",
        "power": 2,
        "coinpower": 5,
        "weight": 1,
        "hit": {
          "start": "[사용시] 자신의 충전 횟수 7 증가\n충전 횟수가 10 이상이면, 코인 위력 +1\n충전 횟수가 15 이상이면, 추가로 코인 위력 +1",
          "h1": "[적중시] 충전 횟수가 10 이상이면, 참격 취약 2 부여",
          "h2": "",
          "h3": "[적중시] 대상의 체력이 30% 미만이면 피해량 +30%\n[적 처치시] 다음 턴에 신속 3 얻음",
          "h4": "",
          "h5": "",
          "end": ""
        }
      },
      "skill3": {
        "skilltype": "공격",
        "skill": "s3",
        "coin": 4,
        "name": "차.마.공.절",
        "level": 40,
        "type": "참격",
        "prop": "질투",
        "power": 3,
        "coinpower": 2,
        "weight": 1,
        "hit": {
          "start": "[사용시] 충전 횟수가 7 이상, 15 미만이면, 보유한 충전 횟수를 전부 소모한 뒤, 최대 체력의 3x(15-소모한 충전 횟수)%만큼 체력을 소모하여 코인 위력 +5\n[사용시] 충전 횟수를 15 소모하여 코인 위력 +5",
          "h1": "[앞면 적중시] 마지막 코인의 피해량 +10%",
          "h2": "[앞면 적중시] 마지막 코인의 피해량 +10%",
          "h3": "[앞면 적중시] 마지막 코인의 피해량 +10%",
          "h4": "[적 처치시] 스킬 사용시 충전 횟수를 15 소모했다면, 자신과 자신을 제외한 무작위 아군 1명에게 충전 역장 7 부여",
          "h5": "",
          "end": ""
        }
      },
      "def": {
        "skilltype": "수비",
        "skill": "s4",
        "coin": 1,
        "name": "충전 회피",
        "level": 31,
        "catype": "",
        "type": "방어",
        "prop": "색욕",
        "power": 4,
        "coinpower": 10,
        "weight": 1,
        "hit": {
          "start": "충전 횟수 5당 기본 위력 +1(최대 3)",
          "h1": "",
          "h2": "",
          "h3": "",
          "h4": "",
          "h5": "",
          "end": ""
        }
      },
      "pass1": {
        "name": "차원 마검",
        "prop": "오만",
        "poss": 5,
        "posstype": "보유",
        "passdescription": "적 처치 시 충전 횟수 3 증가(턴 당 최대 3회 발동)"
      },
      "pass2": {
        "name": "차원 굴절 칼날 - Type: Blade Mk7",
        "prop": "오만",
        "poss": 5,
        "posstype": "보유",
        "passdescription": "최대 체력이 가장 낮은 아군 1명이 적 처치 시 충전 횟수 3 증가(턴 당 최대 1회 발동)"
      }
    },
    "keyword": [
      "W사",
      "료슈",
      "참격",
      "색욕",
      "오만",
      "질투",
      "충전 횟수",
      "참격 취약",
      "신속",
      "충전 역장"
    ]
  },
  {
    "id": 75,
    "birth": "2023/11/16",
    "name": "LCCB 대리",
    "character": "료슈",
    "sync": 4,
    "rank": 2,
    "resistance": ["보통", "내성", "취약"],
    "get": "추출(시즌 3 이후) / 자아 파편 150 교환(시즌 3, 시즌 5 이후)",
    "ticket": "\"난 재밌으려고 [일]한다.\"",
    "season": "3",
    "position": "LCCB",
    "desc": {
      "desc1": [
        "\"료슈, 듣.있. …음? 이렇게 무전하면 안 된다고? 줄여 말하지 말아…? 왜… 신참이라서라고? 하아…\"",
        "RyoShu/LCCB료슈일1.webp"
      ],
      "desc2": [
        "\"여기는 료슈, 작전 편성 인원 전원이 사망해… 뭐야, 무전도 안 듣는군… 좋아, 여기서부터는 내 세상이다.\"",
        "RyoShu/LCCB료슈일2.webp"
      ]
    },
    "sync4": {
      "life": 180,
      "speed": "4-7",
      "defend": 40,
      "skill1": {
        "skilltype": "공격",
        "skill": "s1",
        "coin": 1,
        "name": "밀치기",
        "level": 41,
        "type": "타격",
        "prop": "색욕",
        "power": 5,
        "coinpower": 5,
        "weight": 1,
        "hit": {
          "start": "[사용시] 자신의 호흡 횟수 2 증가\n자신의 호흡이 7 이상이면, 코인 위력 +1",
          "h1": "[크리티컬 적중 시] 대상의 정신력 8 감소",
          "h2": "",
          "h3": "",
          "h4": "",
          "h5": "",
          "end": ""
        }
      },
      "skill2": {
        "skilltype": "공격",
        "skill": "s2",
        "coin": 2,
        "name": "타.무",
        "level": 41,
        "type": "타격",
        "prop": "탐식",
        "power": 4,
        "coinpower": 5,
        "weight": 1,
        "hit": {
          "start": "자신의 호흡이 7 이상이면, 코인 위력 +1",
          "h1": "[적중시] 호흡 2 얻음\n[크리티컬 적중 시] 공격 레벨 감소 2 부여",
          "h2": "[적중시] 호흡 1 얻음\n[크리티컬 적중 시] 공격 레벨 감소 1 부여",
          "h3": "",
          "h4": "",
          "h5": "",
          "end": ""
        }
      },
      "skill3": {
        "skilltype": "공격",
        "skill": "s3",
        "coin": 3,
        "name": "대.박",
        "level": 43,
        "type": "관통",
        "prop": "오만",
        "power": 4,
        "coinpower": 3,
        "weight": 1,
        "hit": {
          "start": "[사용시] 호흡 4 얻음\n자신의 호흡 7당, 코인 위력 +1 (최대 2)",
          "h1": "[크리티컬 적중 시] 자신의 호흡 횟수 1 증가",
          "h2": "[크리티컬 적중 시] 자신의 호흡 횟수 1 증가",
          "h3": "탄환 1 소모\n[크리티컬 적중 시] 진동, 파열의 위력과 횟수가 2배로 부여됨\n[적중시] 진동 4 부여, 진동 횟수 2 증가\n[적중시] 파열 4 부여, 파열 횟수 2 증가\n[적중시] 진동 폭발",
          "h4": "",
          "h5": "",
          "end": ""
        }
      },
      "def": {
        "skilltype": "수비",
        "skill": "s4",
        "coin": 1,
        "name": "가드",
        "level": 43,
        "type": "방어",
        "prop": "탐식",
        "power": 8,
        "coinpower": 8,
        "weight": 1,
        "hit": {
          "start": "",
          "h1": "",
          "h2": "",
          "h3": "",
          "h4": "",
          "h5": "",
          "end": ""
        }
      },
      "pass1": {
        "name": "담.탐",
        "prop": "탐식",
        "poss": 2,
        "posstype": "보유",
        "passdescription": "- 상시 적용: 탄환 7개 보유\n- 턴 종료 시 자신에게 호흡이 7 이상 있으면, 정신력 8 회복\n- 회복 전 정신력이 최대인 경우, 다음 턴에 호흡 1을 얻음"
      },
      "pass2": {
        "name": "돛대",
        "prop": "오만",
        "poss": 4,
        "posstype": "보유",
        "passdescription": "- 탄환을 가장 적게 보유한 아군 1명이 탄환을 소모하는 스킬을 사용할 때, 호흡 3 부여 (턴 당 1회. 탄환이 없는 대상에게는 적용되지 않음)\n- 탄환을 가장 적게 보유한 아군 1명이 스킬에서 마지막 탄환을 소모하면, 공격 종료 시 해당 스킬로 피해를 입힌 대상에게 스킬 피해량의 50%만큼 추가 피해를 줌"
      }
    },
    "sync3": {
      "life": 180,
      "speed": "4-7",
      "defend": 40,
      "skill1": {
        "skilltype": "공격",
        "skill": "s1",
        "coin": 1,
        "name": "밀치기",
        "level": 41,
        "type": "타격",
        "prop": "색욕",
        "power": 5,
        "coinpower": 5,
        "weight": 1,
        "hit": {
          "start": "[사용시] 자신의 호흡 횟수 2 증가",
          "h1": "[크리티컬 적중 시] 대상의 정신력 6 감소",
          "h2": "",
          "h3": "",
          "h4": "",
          "h5": "",
          "end": ""
        }
      },
      "skill2": {
        "skilltype": "공격",
        "skill": "s2",
        "coin": 2,
        "name": "타.무",
        "level": 41,
        "type": "타격",
        "prop": "탐식",
        "power": 4,
        "coinpower": 5,
        "weight": 1,
        "hit": {
          "start": "",
          "h1": "[적중시] 호흡 2 얻음\n[크리티컬 적중 시] 공격 레벨 감소 1 부여",
          "h2": "[적중시] 호흡 1 얻음\n[크리티컬 적중 시] 공격 레벨 감소 1 부여",
          "h3": "",
          "h4": "",
          "h5": "",
          "end": ""
        }
      },
      "skill3": {
        "skilltype": "공격",
        "skill": "s3",
        "coin": 3,
        "name": "대.박",
        "level": 43,
        "type": "관통",
        "prop": "오만",
        "power": 4,
        "coinpower": 3,
        "weight": 1,
        "hit": {
          "start": "[사용시] 호흡 4 얻음\n자신의 호흡이 10 이상이면, 코인 위력 +1",
          "h1": "",
          "h2": "",
          "h3": "탄환 1 소모\n[크리티컬 적중 시] 진동, 파열의 위력과 횟수가 2배로 부여됨\n[적중시] 진동 3 부여, 진동 횟수 1 증가\n[적중시] 파열 3 부여, 파열 횟수 1 증가\n[앞면 적중시] 진동 폭발",
          "h4": "",
          "h5": "",
          "end": ""
        }
      },
      "def": {
        "skilltype": "수비",
        "skill": "s4",
        "coin": 1,
        "name": "가드",
        "level": 43,
        "type": "방어",
        "prop": "없음",
        "power": 8,
        "coinpower": 5,
        "weight": 1,
        "hit": {
          "start": "",
          "h1": "",
          "h2": "",
          "h3": "",
          "h4": "",
          "h5": "",
          "end": ""
        }
      },
      "pass1": {
        "name": "담.탐",
        "prop": "탐식",
        "poss": 2,
        "posstype": "보유",
        "passdescription": "- 상시 적용: 탄환 7개 보유\n- 턴 종료 시 자신에게 호흡이 7 이상 있으면, 정신력 8 회복"
      },
      "pass2": {
        "name": "돛대",
        "prop": "오만",
        "poss": 4,
        "posstype": "보유",
        "passdescription": "- 탄환을 가장 적게 보유한 아군 1명이 스킬에서 마지막 탄환을 소모하면, 공격 종료 시 해당 스킬로 피해를 입힌 대상에게 스킬 피해량의 50%만큼 추가 피해를 줌"
      }
    },
    "keyword": [
      "LCCB",
      "료슈",
      "색욕",
      "탐식",
      "오만",
      "타격",
      "관통",
      "호흡 횟수",
      "호흡",
      "공격 레벨 감소",
      "탄환",
      "진동",
      "파열",
      "진동 폭발"
    ]
  }
]
